HydroRollDiceParser/__init__.py
hydrorolldiceparser-0.1.0.dist-info/METADATA
hydrorolldiceparser-0.1.0.dist-info/WHEEL
hydrorolldiceparser-0.1.0.dist-info/licenses/AUTHORS
hydrorolldiceparser-0.1.0.dist-info/licenses/COPYING.txt
hydrorolldiceparser-0.1.0.dist-info/licenses/LICENSE
hydrorolldiceparser-0.1.0.dist-info/RECORD
